.travis.yml
MANIFEST.in
README.md
VERSION
requirements.txt
setup.py
newslynx_sc_rss/__init__.py
newslynx_sc_rss/_event_options.yaml
newslynx_sc_rss/common.py
newslynx_sc_rss/feed.py
newslynx_sc_rss/feed_to_article.yaml
newslynx_sc_rss/google_alerts.py
newslynx_sc_rss/google_alerts_to_event.yaml
newslynx_sc_rss.egg-info/PKG-INFO
newslynx_sc_rss.egg-info/SOURCES.txt
newslynx_sc_rss.egg-info/dependency_links.txt
newslynx_sc_rss.egg-info/namespace_packages.txt
newslynx_sc_rss.egg-info/not-zip-safe
newslynx_sc_rss.egg-info/requires.txt
newslynx_sc_rss.egg-info/top_level.txt
newslynx_sc_rss/lib/__init__.py
newslynx_sc_rss/lib/feedparser.py