Metadata-Version: 1.1
Name: newslynx-sc-rss
Version: 0.0.5
Summary: This module contains all Sous Chefs which deal with RSS extraction.
Home-page: http://github.com/newslynx/newslynx-sc-rss
Author: Brian Abelson
Author-email: UNKNOWN
License: MIT
Platform: UNKNOWN
Classifier: Development Status :: 3 - Alpha
Classifier: Intended Audience :: Developers
Classifier: License :: OSI Approved :: MIT License
Classifier: Operating System :: OS Independent
Classifier: Programming Language :: Python
